neuronfunc/__init__.py
neuronfunc/nf.py
neuronfunc-0.0.1.dist-info/METADATA
neuronfunc-0.0.1.dist-info/WHEEL
neuronfunc-0.0.1.dist-info/top_level.txt
neuronfunc-0.0.1.dist-info/RECORD
