Metadata-Version: 2.1
Name: neuronfunc
Version: 0.0.1
Summary: A modue to help run the basic neural network function
Home-page: UNKNOWN
Author: Advaith S
Author-email: <popular9adu@gmail.com>
License: UNKNOWN
Keywords: python,ai,python3,neuralnetworks
Platform: UNKNOWN
Classifier: Development Status :: 6 - Mature
Classifier: Intended Audience :: Developers
Classifier: Programming Language :: Python :: 3
Classifier: Operating System :: Unix
Classifier: Operating System :: MacOS :: MacOS X
Classifier: Operating System :: Microsoft :: Windows
